<?xml version="1.0"?>
<!DOCTYPE hibernate-mapping PUBLIC "-//Hibernate/Hibernate Mapping DTD 3.0//EN"
"http://hibernate.sourceforge.net/hibernate-mapping-3.0.dtd">
<!-- Generated Jun 24, 2015 4:52:50 PM by Hibernate Tools 3.4.0.CR1 -->
<hibernate-mapping>
    <class name="com.zstrength.building.pojo.BuildingEnterprises" table="building_enterprises" catalog="snailhouse">
        <id name="entId" type="java.lang.Integer">
            <column name="ent_id" />
            <generator class="identity" />
        </id>
        <property name="buildingId" type="int">
            <column name="building_id" not-null="true">
                <comment>&#229;&#164;&#167;&#230;&#168;&#147;&#228;&#187;&#163;&#231;&#162;&#188;</comment>
            </column>
        </property>
        <property name="entName" type="string">
            <column name="ent_name" length="30">
                <comment>&#229;&#133;&#172;&#229;&#143;&#184;&#229;&#144;&#141;&#231;&#168;&#177;</comment>
            </column>
        </property>
        <property name="floor" type="string">
            <column name="floor" length="20">
                <comment>&#229;&#133;&#172;&#229;&#143;&#184;&#230;&#168;&#147;&#229;&#177;&#164;</comment>
            </column>
        </property>
        <property name="content" type="string">
            <column name="content" length="500" not-null="true">
                <comment>&#231;&#135;&#159;&#230;&#165;&#173;&#229;&#133;&#167;&#229;&#174;&#185;</comment>
            </column>
        </property>
        <property name="url" type="string">
            <column name="url" length="70">
                <comment>&#229;&#133;&#172;&#229;&#143;&#184;&#231;&#182;&#178;&#229;&#157;&#128;</comment>
            </column>
        </property>
        <property name="tel" type="string">
            <column name="tel" length="20">
                <comment>&#229;&#133;&#172;&#229;&#143;&#184;&#233;&#155;&#187;&#232;&#169;&#177;</comment>
            </column>
        </property>
        <property name="logoUrl" type="string">
            <column name="logo_url" length="70">
                <comment>logo&#231;&#182;&#178;&#229;&#157;&#128;</comment>
            </column>
        </property>
        <property name="valid" type="java.lang.Boolean">
            <column name="valid">
                <comment>&#230;&#156;&#137;&#230;&#149;&#136;&#232;&#179;&#135;&#232;&#168;&#138;</comment>
            </column>
        </property>
        <property name="createdId" type="java.lang.Integer">
            <column name="created_id">
                <comment>&#229;&#187;&#186;&#231;&#171;&#139;&#232;&#128;&#133;</comment>
            </column>
        </property>
        <property name="createdDatetime" type="timestamp">
            <column name="created_datetime" length="19">
                <comment>&#229;&#187;&#186;&#231;&#171;&#139;&#230;&#153;&#130;&#233;&#150;&#147;</comment>
            </column>
        </property>
    </class>
</hibernate-mapping>
